MANIFEST.in
setup.py
sunscreen_web3/__init__.py
sunscreen_web3.egg-info/PKG-INFO
sunscreen_web3.egg-info/SOURCES.txt
sunscreen_web3.egg-info/dependency_links.txt
sunscreen_web3.egg-info/requires.txt
sunscreen_web3.egg-info/top_level.txt
sunscreen_web3/c_libs/__init__.py
sunscreen_web3/c_libs/linux.so
sunscreen_web3/c_libs/osx.dylib
sunscreen_web3/c_libs/__pycache__/__init__.cpython-311.pyc
sunscreen_web3/encryption/__init__.py
sunscreen_web3/encryption/buffer.py
sunscreen_web3/encryption/context.py
sunscreen_web3/encryption/encrypted.py
sunscreen_web3/encryption/encryptedfloat64.py
sunscreen_web3/encryption/encryptedsigned.py
sunscreen_web3/encryption/encryptedunsigned256.py
sunscreen_web3/encryption/encryptedunsigned64.py
sunscreen_web3/encryption/rustlibrary.py
sunscreen_web3/web3/__init__.py
sunscreen_web3/web3/sunscreen_web3.py