Metadata-Version: 2.1
Name: sunscreen-web3
Version: 0.0.13
Summary: Sunscreen Web 3 Python Interop Package
Author: SmartFHE
Author-email: hello@sunscreen.tch
Keywords: cryptography,sunscreen,fhe,bfv,web3
